instadownloader.py
instadownloader-0.0.1.dist-info/License.txt
instadownloader-0.0.1.dist-info/METADATA
instadownloader-0.0.1.dist-info/WHEEL
instadownloader-0.0.1.dist-info/top_level.txt
instadownloader-0.0.1.dist-info/RECORD
