Metadata-Version: 2.1
Name: instadownloader
Version: 0.0.1
Summary: A photo-scraping and photo-storage tool used for generating training sets
Home-page: https://github.com/baileymorton989/instadownloader
Author: Bailey Morton
Author-email: baileymorton989@gmail.com
License: MIT License
Platform: UNKNOWN
Classifier: Programming Language :: Python :: 3
Classifier: Programming Language :: Python :: 3.6
Classifier: Programming Language :: Python :: 3.7
Classifier: Programming Language :: Python :: 3.8
Classifier: Programming Language :: Python :: 3.9
Classifier: License :: OSI Approved :: MIT License
Classifier: Operating System :: OS Independent
Provides-Extra: dev
